heroku_applink/__init__.py
heroku_applink/authorization.py
heroku_applink/config.py
heroku_applink/connection.py
heroku_applink/context.py
heroku_applink/exceptions.py
heroku_applink/middleware.py
heroku_applink/data_api/__init__.py
heroku_applink/data_api/_requests.py
heroku_applink/data_api/exceptions.py
heroku_applink/data_api/record.py
heroku_applink/data_api/reference_id.py
heroku_applink/data_api/unit_of_work.py
heroku_applink-1.1.4.dist-info/METADATA
heroku_applink-1.1.4.dist-info/WHEEL
heroku_applink-1.1.4.dist-info/licenses/LICENSE
heroku_applink-1.1.4.dist-info/RECORD
