Metadata-Version: 2.4
Name: heroku_applink
Version: 1.1.4
Summary: Simple SDK for Heroku AppLink and Salesforce development
Project-URL: Homepage, https://github.com/heroku/heroku-applink-python
Project-URL: Documentation, https://github.com/heroku/heroku-applink-python
Project-URL: Repository, https://github.com/heroku/heroku-applink-python.git
Project-URL: Bug Tracker, https://github.com/heroku/heroku-applink-python/issues
Project-URL: Changelog, https://github.com/heroku/heroku-applink-python/CHANGELOG.md
License-File: LICENSE
Requires-Python: >=3.10
Requires-Dist: aiohttp>=3.11.12
Requires-Dist: orjson>=3.10.15
Requires-Dist: yarl>=1.20.0
Provides-Extra: dev
Requires-Dist: pdoc3>=0.11.0; extra == 'dev'
Requires-Dist: ruff>=0.1.0; extra == 'dev'
Requires-Dist: tox-uv>=0.1.0; extra == 'dev'
Requires-Dist: tox>=4.0.0; extra == 'dev'
Provides-Extra: test
Requires-Dist: aioresponses>=0.7.8; extra == 'test'
Requires-Dist: coverage>=7.0.0; extra == 'test'
Requires-Dist: fastapi>=0.115.0; extra == 'test'
Requires-Dist: flask>=3.1.1; extra == 'test'
Requires-Dist: httpx>=0.28.1; extra == 'test'
Requires-Dist: pytest-asyncio>=0.21.0; extra == 'test'
Requires-Dist: pytest-cov>=4.0.0; extra == 'test'
Requires-Dist: pytest-mock>=3.10.0; extra == 'test'
Requires-Dist: pytest>=7.0.0; extra == 'test'
Requires-Dist: ruff>=0.1.0; extra == 'test'
Requires-Dist: uvicorn>=0.34.0; extra == 'test'
